[[["break", [[[31, "figure7s", 3]], [[31, "figure7s", 6], [4, "bone", 11]], [[30, "figure7g", 3], [36, "heart", 1], [48, "powder", 10]], [[30, "figure7g", 6], [36, "heart", 2], [47, "potion", 6]]]], ["skill", [[[68, "sphere07", 3]], [[68, "sphere07", 6]], [[57, "ruby07", 3]], [[57, "ruby07", 6], [48, "powder", 5]], [[75, "star07", 3], [48, "powder", 10]], [[75, "star07", 6], [4, "bone", 8]], [[4, "bone", 15], [45, "paper", 3]], [[45, "paper", 9], [47, "potion", 12]], [[10, "cubes", 1]]]]], [[[48, {"needed_num": 10, "item_name": "powder"}], [36, {"needed_num": 3, "item_name": "heart"}], [4, {"needed_num": 11, "item_name": "bone"}], [47, {"needed_num": 6, "item_name": "potion"}], [30, {"needed_num": 9, "item_name": "figure7g"}], [31, {"needed_num": 9, "item_name": "figure7s"}]], [[48, {"needed_num": 45, "item_name": "powder"}], [68, {"needed_num": 27, "item_name": "sphere07"}], [57, {"needed_num": 27, "item_name": "ruby07"}], [10, {"needed_num": 3, "item_name": "cubes"}], [75, {"needed_num": 27, "item_name": "star07"}], [45, {"needed_num": 36, "item_name": "paper"}], [4, {"needed_num": 69, "item_name": "bone"}], [47, {"needed_num": 36, "item_name": "potion"}]]], [[4, "bone", 80], [48, "powder", 55], [45, "paper", 36], [47, "potion", 42], [36, "heart", 3], [10, "cubes", 3], [68, "sphere07", 27], [57, "ruby07", 27], [75, "star07", 27], [31, "figure7s", 9], [30, "figure7g", 9]]]