[[["break", [[[14, "duandai", 1]], [[14, "duandai", 1]], [[14, "duandai", 1]], [[14, "duandai", 1]]]], ["skill", [[[64, "sphere05", 4], [63, "sphere04", 4]], [[64, "sphere05", 10], [63, "sphere04", 10]], [[53, "ruby05", 4], [52, "ruby04", 4]], [[53, "ruby05", 10], [52, "ruby04", 10]], [[71, "star05", 4], [70, "star04", 4]], [[71, "star05", 10], [70, "star04", 10]], [[79, "yinmao", 4], [12, "deng", 4]], [[48, "root", 7], [32, "gem", 7]], [[10, "cubes", 1]]]]], [[[14, {"needed_num": 4, "item_name": "duandai"}]], [[64, {"needed_num": 42, "item_name": "sphere05"}], [48, {"needed_num": 21, "item_name": "root"}], [52, {"needed_num": 42, "item_name": "ruby04"}], [53, {"needed_num": 42, "item_name": "ruby05"}], [70, {"needed_num": 42, "item_name": "star04"}], [71, {"needed_num": 42, "item_name": "star05"}], [32, {"needed_num": 21, "item_name": "gem"}], [79, {"needed_num": 12, "item_name": "yinmao"}], [12, {"needed_num": 12, "item_name": "deng"}], [10, {"needed_num": 3, "item_name": "cubes"}], [63, {"needed_num": 42, "item_name": "sphere04"}]]], [[14, "duandai", 4], [12, "deng", 12], [32, "gem", 21], [48, "root", 21], [79, "yinmao", 12], [10, "cubes", 3], [63, "sphere04", 42], [64, "sphere05", 42], [52, "ruby04", 42], [53, "ruby05", 42], [70, "star04", 42], [71, "star05", 42]]]